LICENSE
MANIFEST.in
README.md
setup.cfg
setup.py
TinkerTest.egg-info/PKG-INFO
TinkerTest.egg-info/SOURCES.txt
TinkerTest.egg-info/dependency_links.txt
TinkerTest.egg-info/entry_points.txt
TinkerTest.egg-info/top_level.txt
tinkertest/__init__.py
tinkertest/tinkertest.py
tinkertest/test/__init__.py
tinkertest/test/test_tinkertest.py