Metadata-Version: 2.1
Name: TinkerTest
Version: 0.1.1
Summary: TinkerTest is a tool designed to make data validation fun!
Home-page: https://github.com/austinv11/tinkertest
Author: austinv11
Author-email: austinv11@gmail.com
License: Apache License 2.0
Project-URL: Source, https://github.com/austinv11/tinkertest/
Project-URL: Bug Reports, https://github.com/austinv11/tinkertest/issues
Keywords: testing test annotations validation
Platform: UNKNOWN
Classifier: Programming Language :: Python :: 3
Classifier: Programming Language :: Python :: 3.6
Classifier: Programming Language :: Python :: 3.7
Classifier: License :: OSI Approved :: Apache Software License
Classifier: Topic :: Software Development :: Build Tools
Classifier: Topic :: Software Development :: Testing
Classifier: Topic :: Software Development :: Testing :: Unit
Classifier: Topic :: Utilities
Classifier: Operating System :: OS Independent
Classifier: Development Status :: 4 - Beta
